kube/__init__.py
kube/_base.py
kube/_cluster.py
kube/_error.py
kube/_meta.py
kube/_namespace.py
kube/_node.py
kube/_pod.py
kube/_replicaset.py
kube/_secret.py
kube/_service.py
kube/_testing.py
kube/_util.py
kube/_watch.py
kube-0.9.1.dist-info/DESCRIPTION.rst
kube-0.9.1.dist-info/METADATA
kube-0.9.1.dist-info/RECORD
kube-0.9.1.dist-info/WHEEL
kube-0.9.1.dist-info/metadata.json
kube-0.9.1.dist-info/top_level.txt
