Metadata-Version: 2.0
Name: kube
Version: 0.9.1
Summary: Opinionated interface for the Kubernetes API
Home-page: http://bitbucket.org/cobeio/kube
Author: Floris Bruynooghe
Author-email: flub@cobe.io
License: LGPLv3
Keywords: kubernetes k8s watch
Platform: UNKNOWN
Classifier: Development Status :: 4 - Beta
Classifier: Intended Audience :: Developers
Classifier: License :: OSI Approved :: GNU Lesser General Public License v3 (LGPLv3)
Classifier: Topic :: Software Development :: Libraries
Classifier: Programming Language :: Python :: 3 :: Only
Classifier: Programming Language :: Python :: 3.4
Classifier: Programming Language :: Python :: 3.5
Requires-Dist: http-parser
Requires-Dist: pyrsistent
Requires-Dist: requests
